promptboot/__init__.py
promptboot/async_client.py
promptboot/client.py
promptboot/config.py
promptboot/logs/__init__.py
promptboot/logs/log_manager.py
promptboot/logs/logger.py
promptboot-0.1.1.dist-info/METADATA
promptboot-0.1.1.dist-info/WHEEL
promptboot-0.1.1.dist-info/top_level.txt
promptboot-0.1.1.dist-info/RECORD
