Metadata-Version: 2.4
Name: promptboot
Version: 0.1.1
Summary: A micro framework for bootstrapping AI applications with prompt engineering
Home-page: https://github.com/yalinfeng/promptboot
Author: Yalin Feng
Author-email: Yalin Feng <yalinfeng@outlook.com>
License: MIT
Project-URL: Homepage, https://github.com/yalinfeng/promptboot
Classifier: Development Status :: 3 - Alpha
Classifier: Intended Audience :: Developers
Classifier: License :: OSI Approved :: MIT License
Classifier: Operating System :: OS Independent
Classifier: Programming Language :: Python :: 3
Classifier: Programming Language :: Python :: 3.8
Classifier: Programming Language :: Python :: 3.9
Classifier: Programming Language :: Python :: 3.10
Classifier: Programming Language :: Python :: 3.11
Classifier: Topic :: Software Development :: Libraries :: Python Modules
Requires-Python: >=3.8
Requires-Dist: openai
Requires-Dist: tenacity
Requires-Dist: pydantic
Requires-Dist: pyyaml
Provides-Extra: dev
Requires-Dist: pytest>=6.0; extra == "dev"
Requires-Dist: black; extra == "dev"
Requires-Dist: flake8; extra == "dev"
Dynamic: author
Dynamic: home-page
Dynamic: requires-python
